{
    "stake_currency": "USDC",
    "stake_amount": "unlimited",
    "tradable_balance_ratio": 0.95,
    "available_capital": 100,
    "dry_run": false,
    "dry_run_wallet": 0.1001,
    "cancel_open_orders_on_exit": true,
    "trading_mode": "futures",
    "margin_mode": "isolated",
    "process_only_new_candles": true,
    "unfilledtimeout": {
        "entry": 10,
        "exit": 10,
        "exit_timeout_count": 0,
        "unit": "minutes"
    },
    "entry_pricing": {
        "price_side": "same",
        "price_last_balance": 1.0,
        "use_order_book": true,
        "order_book_top": 1
    },
    "exit_pricing": {
        "price_side": "same",
        "price_last_balance": 1.0,
        "use_order_book": true,
        "order_book_top": 1
    },
    "edge": {
        "enabled": false,
        "process_throttle_secs": 3600,
        "calculate_since_number_of_days": 7,
        "allowed_risk": 0.01,
        "stoploss_range_min": -0.01,
        "stoploss_range_max": -0.1,
        "stoploss_range_step": -0.01,
        "minimum_winrate": 0.60,
        "minimum_expectancy": 0.20,
        "min_trade_number": 10,
        "max_trade_duration_minute": 1440,
        "remove_pumps": false
    },
    "telegram": {
        "enabled": false,
        "token": "",
        "chat_id": ""
    },
    "api_server": {
        "enabled": true,
        "listen_ip_address": "0.0.0.0",
        "verbosity": "error",
        "enable_openapi": false
    },
    "exchange": {
        "pair_whitelist": [
            "AAVE/USDC:USDC","ACE/USDC:USDC","ADA/USDC:USDC","AI/USDC:USDC","AI16Z/USDC:USDC","AIXBT/USDC:USDC","ALGO/USDC:USDC","ALT/USDC:USDC","ANIME/USDC:USDC","APE/USDC:USDC","APT/USDC:USDC","AR/USDC:USDC","ARB/USDC:USDC","ARK/USDC:USDC","ATOM/USDC:USDC","AVAX/USDC:USDC","BADGER/USDC:USDC","BANANA/USDC:USDC","BCH/USDC:USDC","BERA/USDC:USDC","BIGTIME/USDC:USDC","BIO/USDC:USDC","BLAST/USDC:USDC","BLUR/USDC:USDC","BNB/USDC:USDC","BOME/USDC:USDC","BRETT/USDC:USDC","BSV/USDC:USDC","BTC/USDC:USDC","CAKE/USDC:USDC","CATI/USDC:USDC","CELO/USDC:USDC","CFX/USDC:USDC","CHILLGUY/USDC:USDC","COMP/USDC:USDC","CRV/USDC:USDC","CYBER/USDC:USDC","DOGE/USDC:USDC","DOT/USDC:USDC","DYDX/USDC:USDC","DYM/USDC:USDC","EIGEN/USDC:USDC","ENA/USDC:USDC","ENS/USDC:USDC","ETC/USDC:USDC","ETH/USDC:USDC","ETHFI/USDC:USDC","FARTCOIN/USDC:USDC","FET/USDC:USDC","FIL/USDC:USDC","FTT/USDC:USDC","FXS/USDC:USDC","GALA/USDC:USDC","GAS/USDC:USDC","GMT/USDC:USDC","GMX/USDC:USDC","GOAT/USDC:USDC","GRASS/USDC:USDC","GRIFFAIN/USDC:USDC","HBAR/USDC:USDC","HMSTR/USDC:USDC","HYPE/USDC:USDC","IMX/USDC:USDC","INJ/USDC:USDC","IO/USDC:USDC","IOTA/USDC:USDC","IP/USDC:USDC","JTO/USDC:USDC","JUP/USDC:USDC","KAITO/USDC:USDC","KAS/USDC:USDC","LAYER/USDC:USDC","LDO/USDC:USDC","LINK/USDC:USDC","LISTA/USDC:USDC","LTC/USDC:USDC","MANTA/USDC:USDC","MAV/USDC:USDC","MAVIA/USDC:USDC","ME/USDC:USDC","MELANIA/USDC:USDC","MEME/USDC:USDC","MERL/USDC:USDC","MEW/USDC:USDC","MINA/USDC:USDC","MKR/USDC:USDC","MNT/USDC:USDC","MOODENG/USDC:USDC","MORPHO/USDC:USDC","MOVE/USDC:USDC","NEAR/USDC:USDC","NEIROETH/USDC:USDC","NEO/USDC:USDC","NIL/USDC:USDC","NOT/USDC:USDC","OGN/USDC:USDC","OM/USDC:USDC","OMNI/USDC:USDC","ONDO/USDC:USDC","OP/USDC:USDC","ORDI/USDC:USDC","PAXG/USDC:USDC","PENDLE/USDC:USDC","PENGU/USDC:USDC","PEOPLE/USDC:USDC","PIXEL/USDC:USDC","PNUT/USDC:USDC","POL/USDC:USDC","POLYX/USDC:USDC","POPCAT/USDC:USDC","PURR/USDC:USDC","PYTH/USDC:USDC","RDNT/USDC:USDC","RENDER/USDC:USDC","REQ/USDC:USDC","REZ/USDC:USDC","RSR/USDC:USDC","RUNE/USDC:USDC","S/USDC:USDC","SAGA/USDC:USDC","SAND/USDC:USDC","SCR/USDC:USDC","SEI/USDC:USDC","SNX/USDC:USDC","SOL/USDC:USDC","SPX/USDC:USDC","STG/USDC:USDC","STRK/USDC:USDC","STX/USDC:USDC","SUI/USDC:USDC","SUPER/USDC:USDC","SUSHI/USDC:USDC","TAO/USDC:USDC","TIA/USDC:USDC","TNSR/USDC:USDC","TON/USDC:USDC","TRB/USDC:USDC","TRUMP/USDC:USDC","TRX/USDC:USDC","TST/USDC:USDC","TURBO/USDC:USDC","UMA/USDC:USDC","UNI/USDC:USDC","USTC/USDC:USDC","USUAL/USDC:USDC","VINE/USDC:USDC","VIRTUAL/USDC:USDC","VVV/USDC:USDC","W/USDC:USDC","WIF/USDC:USDC","WLD/USDC:USDC","XAI/USDC:USDC","XLM/USDC:USDC","XRP/USDC:USDC","YGG/USDC:USDC","ZEN/USDC:USDC","ZEREBRO/USDC:USDC","ZETA/USDC:USDC","ZK/USDC:USDC","ZRO/USDC:USDC","kBONK/USDC:USDC","kDOGS/USDC:USDC","kFLOKI/USDC:USDC","kLUNC/USDC:USDC","kNEIRO/USDC:USDC","kPEPE/USDC:USDC","kSHIB/USDC:USDC"
        ],
        "pair_blacklist": [
            "EUR/.*",
            "USDT/.*",
            "UST/.*",
            "USDC/USDT",
            "USDE/USDT",
            "PYUSD/USDT"
        ],
        "ccxt_async_config": {
            "enableRateLimit": true,
            "rateLimit": 700
        }
    },
    "initial_state": "running",
    "force_entry_enable": false
}
